idlegame/__init__.py
idlegame/battle.py
idlegame/config.py
idlegame/data.py
idlegame/idle.py
idlegame/main.py
idlegame/nanobots.py
idlegame/packages.py
idlegame/profile.py
tests/__init__.py
tests/testing.py
idlegame-2.0.1.1.dist-info/LICENSE
idlegame-2.0.1.1.dist-info/METADATA
idlegame-2.0.1.1.dist-info/WHEEL
idlegame-2.0.1.1.dist-info/entry_points.txt
idlegame-2.0.1.1.dist-info/top_level.txt
idlegame-2.0.1.1.dist-info/RECORD
