Metadata-Version: 2.1
Name: idlegame
Version: 2.0.1.1
Summary: A tiny idle game you can play right from your terminal, if you are bored at your software development job
Author: Ben Boonstra
License: MIT
Requires-Python: >=3.6
License-File: LICENSE
Requires-Dist: colorama
